<?xml version="1.0" encoding="utf-8" ?>
<dwsync>
<file name="dataTables.bootstrap.css" server="apartahotel7maravillas.com//public_html/sw/" local="131497871740000000" remote="131667025200000000" Dst="0" />
<file name="dataTables.bootstrap.min.css" server="apartahotel7maravillas.com//public_html/sw/" local="131497871740000000" remote="131667025200000000" Dst="0" />
<file name="dataTables.bootstrap4.css" server="apartahotel7maravillas.com//public_html/sw/" local="131497871740000000" remote="131667025200000000" Dst="0" />
<file name="dataTables.bootstrap4.min.css" server="apartahotel7maravillas.com//public_html/sw/" local="131497871740000000" remote="131667025200000000" Dst="0" />
<file name="dataTables.foundation.css" server="apartahotel7maravillas.com//public_html/sw/" local="131497871740000000" remote="131667025200000000" Dst="0" />
<file name="dataTables.foundation.min.css" server="apartahotel7maravillas.com//public_html/sw/" local="131497871740000000" remote="131667025200000000" Dst="0" />
<file name="dataTables.jqueryui.css" server="apartahotel7maravillas.com//public_html/sw/" local="131497871740000000" remote="131667025200000000" Dst="0" />
<file name="dataTables.jqueryui.min.css" server="apartahotel7maravillas.com//public_html/sw/" local="131497871740000000" remote="131667025200000000" Dst="0" />
<file name="dataTables.semanticui.css" server="apartahotel7maravillas.com//public_html/sw/" local="131497871740000000" remote="131667025200000000" Dst="0" />
<file name="dataTables.semanticui.min.css" server="apartahotel7maravillas.com//public_html/sw/" local="131497871740000000" remote="131667025200000000" Dst="0" />
<file name="jquery.dataTables.css" server="apartahotel7maravillas.com//public_html/sw/" local="131497871740000000" remote="131667025200000000" Dst="0" />
<file name="jquery.dataTables.min.css" server="apartahotel7maravillas.com//public_html/sw/" local="131497871740000000" remote="131667025200000000" Dst="0" />
</dwsync>